PythonHexinBianchengDierBanFix1/README.md
PythonHexinBianchengDierBanFix1/__init__.py
PythonHexinBianchengDierBanFix1/__main__.py
PythonHexinBianchengDierBanFix1/file.epub
PythonHexinBianchengDierBanFix1/index.html
PythonHexinBianchengDierBanFix1/css/__init__.py
PythonHexinBianchengDierBanFix1/css/annotations.css
PythonHexinBianchengDierBanFix1/css/main.css
PythonHexinBianchengDierBanFix1/css/normalize.css
PythonHexinBianchengDierBanFix1/css/popup.css
PythonHexinBianchengDierBanFix1/font/__init__.py
PythonHexinBianchengDierBanFix1/font/fontello.eot
PythonHexinBianchengDierBanFix1/font/fontello.svg
PythonHexinBianchengDierBanFix1/font/fontello.ttf
PythonHexinBianchengDierBanFix1/font/fontello.woff
PythonHexinBianchengDierBanFix1/img/__init__.py
PythonHexinBianchengDierBanFix1/img/annotator-glyph-sprite.png
PythonHexinBianchengDierBanFix1/img/annotator-icon-sprite.png
PythonHexinBianchengDierBanFix1/img/apple-touch-icon.png
PythonHexinBianchengDierBanFix1/img/cancelfullscreen.png
PythonHexinBianchengDierBanFix1/img/close.png
PythonHexinBianchengDierBanFix1/img/fullscreen.png
PythonHexinBianchengDierBanFix1/img/loader.gif
PythonHexinBianchengDierBanFix1/img/menu-icon.png
PythonHexinBianchengDierBanFix1/img/save.png
PythonHexinBianchengDierBanFix1/img/saved.png
PythonHexinBianchengDierBanFix1/img/settings-s.png
PythonHexinBianchengDierBanFix1/img/settings.png
PythonHexinBianchengDierBanFix1/img/star.png
PythonHexinBianchengDierBanFix1/js/__init__.py
PythonHexinBianchengDierBanFix1/js/epub.js
PythonHexinBianchengDierBanFix1/js/epub.min.js
PythonHexinBianchengDierBanFix1/js/epub.min.map
PythonHexinBianchengDierBanFix1/js/hooks.min.js
PythonHexinBianchengDierBanFix1/js/hooks.min.map
PythonHexinBianchengDierBanFix1/js/reader.js
PythonHexinBianchengDierBanFix1/js/reader.js.map
PythonHexinBianchengDierBanFix1/js/reader.min.js
PythonHexinBianchengDierBanFix1/js/reader.min.map
PythonHexinBianchengDierBanFix1/js/hooks/__init__.py
python_hexin_biancheng_dier_ban_fix1-2024.3.1.0.dist-info/METADATA
python_hexin_biancheng_dier_ban_fix1-2024.3.1.0.dist-info/WHEEL
python_hexin_biancheng_dier_ban_fix1-2024.3.1.0.dist-info/entry_points.txt
python_hexin_biancheng_dier_ban_fix1-2024.3.1.0.dist-info/top_level.txt
python_hexin_biancheng_dier_ban_fix1-2024.3.1.0.dist-info/RECORD
